LICENSE
setup.py
addons/__init__.py
addons/mod3.py
random_generate.egg-info/PKG-INFO
random_generate.egg-info/SOURCES.txt
random_generate.egg-info/dependency_links.txt
random_generate.egg-info/top_level.txt