Metadata-Version: 2.1
Name: random-generate
Version: 0.1.1
Summary: This is a package created for random generating JSON, Numbers and passwords
Home-page: https://github.com/varunkatiyar819/random_generate
Author: Varun Katiyar
Author-email: varunkatiyar819@gmail.com
License: UNKNOWN
Platform: UNKNOWN
License-File: LICENSE
